mwsimpleedittypes/__init__.py
mwsimpleedittypes/constants.py
mwsimpleedittypes/differ.py
mwsimpleedittypes/mwsimpleedittypes.py
mwsimpleedittypes/tokenizer.py
mwsimpleedittypes-1.2.5.dist-info/LICENSE
mwsimpleedittypes-1.2.5.dist-info/METADATA
mwsimpleedittypes-1.2.5.dist-info/WHEEL
mwsimpleedittypes-1.2.5.dist-info/top_level.txt
mwsimpleedittypes-1.2.5.dist-info/RECORD
